envoy/dependency/pip_check/__init__.py
envoy/dependency/pip_check/abstract.py
envoy/dependency/pip_check/checker.py
envoy/dependency/pip_check/cmd.py
envoy/dependency/pip_check/exceptions.py
envoy/dependency/pip_check/py.typed
envoy.dependency.pip_check-0.1.4.dist-info/METADATA
envoy.dependency.pip_check-0.1.4.dist-info/WHEEL
envoy.dependency.pip_check-0.1.4.dist-info/entry_points.txt
envoy.dependency.pip_check-0.1.4.dist-info/namespace_packages.txt
envoy.dependency.pip_check-0.1.4.dist-info/top_level.txt
envoy.dependency.pip_check-0.1.4.dist-info/RECORD
