Metadata-Version: 2.1
Name: envoy.dependency.pip-check
Version: 0.1.4
Summary: "Pip dependabot checker used in Envoy proxy's CI"
Home-page: https://github.com/envoyproxy/pytooling/tree/main/envoy.dependency.pip_check
Author: Ryan Northey
Author-email: ryan@synca.io
Maintainer: Ryan Northey
Maintainer-email: ryan@synca.io
License: Apache Software License 2.0
Platform: UNKNOWN
Requires-Dist: abstracts (>=0.0.12)
Requires-Dist: aio.run.checker (>=0.5.7)
Requires-Dist: envoy.base.utils (>=0.3.9)
